point_transformer_pytorch/__init__.py
point_transformer_pytorch/multihead_point_transformer_pytorch.py
point_transformer_pytorch/point_transformer_pytorch.py
point_transformer_pytorch-0.1.5.dist-info/LICENSE
point_transformer_pytorch-0.1.5.dist-info/METADATA
point_transformer_pytorch-0.1.5.dist-info/WHEEL
point_transformer_pytorch-0.1.5.dist-info/top_level.txt
point_transformer_pytorch-0.1.5.dist-info/RECORD
